{
    "fechas": [
        {
            "fecha": "2025-09-08",
            "torneos": [
                {
                    "id": "14",
                    "nombre": "Copa Argentina",
                    "eventos": [
                        {
                            "id": "80910",
                            "fecha": "2025-09-08 21:10:00",
                            "nombre": "Argentinos Jrs. vs. Lanús",
                            "horaDia": 3,
                            "canales": [
                                {
                                    "id": "20",
                                    "nombre": "TYC SPORTS",
                                    "plataformas": [
                                        "HD",
                                        "ANALOGICO",
                                        "ISDBT",
                                        "IPTV"
                                    ],
                                    "frecuencias": {
                                        "HD": 23,
                                        "ANALOGICO": 17,
                                        "ISDBT": 24.5,
                                        "IPTV": 17
                                    }
                                },
                                {
                                    "id": "50",
                                    "nombre": "TYC SPORTS PLAY"
                                }
                            ],
                            "deporte": {
                                "id": "1",
                                "nombre": "Fútbol",
                                "icono": "futbol.png"
                            }
                        }
                    ],
                    "deporte": {
                        "id": "1",
                        "nombre": "Fútbol",
                        "icono": "futbol.png"
                    },
                    "primerFecha": "2025-09-08 21:10:00",
                    "cantidad_eventos": 1
                },
                {
                    "id": "6",
                    "nombre": "Primera Nacional",
                    "eventos": [
                        {
                            "id": "80911",
                            "fecha": "2025-09-08 15:00:00",
                            "nombre": "Arsenal vs. Tristan Suárez",
                            "horaDia": 2,
                            "canales": [
                                {
                                    "id": "50",
                                    "nombre": "TYC SPORTS PLAY"
                                }
                            ],
                            "deporte": {
                                "id": "1",
                                "nombre": "Fútbol",
                                "icono": "futbol.png"
                            }
                        },
                        {
                            "id": "80912",
                            "fecha": "2025-09-08 15:00:00",
                            "nombre": "Alvarado vs. Deportivo Maipú",
                            "horaDia": 2,
                            "canales": [
                                {
                                    "id": "50",
                                    "nombre": "TYC SPORTS PLAY"
                                }
                            ],
                            "deporte": {
                                "id": "1",
                                "nombre": "Fútbol",
                                "icono": "futbol.png"
                            }
                        },
                        {
                            "id": "80913",
                            "fecha": "2025-09-08 16:00:00",
                            "nombre": "Almirante Brown vs. San Telmo",
                            "horaDia": 2,
                            "canales": [
                                {
                                    "id": "50",
                                    "nombre": "TYC SPORTS PLAY"
                                }
                            ],
                            "deporte": {
                                "id": "1",
                                "nombre": "Fútbol",
                                "icono": "futbol.png"
                            }
                        },
                        {
                            "id": "80914",
                            "fecha": "2025-09-08 19:00:00",
                            "nombre": "Quilmes vs. Ferro",
                            "horaDia": 2,
                            "canales": [
                                {
                                    "id": "20",
                                    "nombre": "TYC SPORTS",
                                    "plataformas": [
                                        "HD",
                                        "ANALOGICO",
                                        "ISDBT",
                                        "IPTV"
                                    ],
                                    "frecuencias": {
                                        "HD": 23,
                                        "ANALOGICO": 17,
                                        "ISDBT": 24.5,
                                        "IPTV": 17
                                    }
                                },
                                {
                                    "id": "50",
                                    "nombre": "TYC SPORTS PLAY"
                                }
                            ],
                            "deporte": {
                                "id": "1",
                                "nombre": "Fútbol",
                                "icono": "futbol.png"
                            }
                        },
                        {
                            "id": "80915",
                            "fecha": "2025-09-08 19:00:00",
                            "nombre": "Colón vs. Estudiantes (RC)",
                            "horaDia": 2,
                            "canales": [
                                {
                                    "id": "20",
                                    "nombre": "TYC SPORTS",
                                    "plataformas": [
                                        "HD",
                                        "ANALOGICO",
                                        "ISDBT",
                                        "IPTV"
                                    ],
                                    "frecuencias": {
                                        "HD": 23,
                                        "ANALOGICO": 17,
                                        "ISDBT": 24.5,
                                        "IPTV": 17
                                    }
                                },
                                {
                                    "id": "50",
                                    "nombre": "TYC SPORTS PLAY"
                                }
                            ],
                            "deporte": {
                                "id": "1",
                                "nombre": "Fútbol",
                                "icono": "futbol.png"
                            }
                        }
                    ],
                    "deporte": {
                        "id": "1",
                        "nombre": "Fútbol",
                        "icono": "futbol.png"
                    },
                    "primerFecha": "2025-09-08 15:00:00",
                    "cantidad_eventos": 5
                },
                {
                    "id": "838",
                    "nombre": "Amistoso Internacional",
                    "eventos": [
                        {
                            "id": "80928",
                            "fecha": "2025-09-08 14:15:00",
                            "nombre": "Chequia vs. Arabia Saudita",
                            "horaDia": 2,
                            "canales": [
                                {
                                    "id": "181",
                                    "nombre": "DISNEY + PREMIUM "
                                }
                            ],
                            "deporte": {
                                "id": "1",
                                "nombre": "Fútbol",
                                "icono": "futbol.png"
                            }
                        }
                    ],
                    "deporte": {
                        "id": "1",
                        "nombre": "Fútbol",
                        "icono": "futbol.png"
                    },
                    "primerFecha": "2025-09-08 14:15:00",
                    "cantidad_eventos": 1
                },
                {
                    "id": "61",
                    "nombre": "Primera B Metropolitana",
                    "eventos": [
                        {
                            "id": "80916",
                            "fecha": "2025-09-08 15:30:00",
                            "nombre": "UAI Urquiza vs. Real Pilar",
                            "horaDia": 2,
                            "canales": [
                                {
                                    "id": "20",
                                    "nombre": "TYC SPORTS",
                                    "plataformas": [
                                        "HD",
                                        "ANALOGICO",
                                        "ISDBT",
                                        "IPTV"
                                    ],
                                    "frecuencias": {
                                        "HD": 23,
                                        "ANALOGICO": 17,
                                        "ISDBT": 24.5,
                                        "IPTV": 17
                                    }
                                },
                                {
                                    "id": "50",
                                    "nombre": "TYC SPORTS PLAY"
                                }
                            ],
                            "deporte": {
                                "id": "1",
                                "nombre": "Fútbol",
                                "icono": "futbol.png"
                            }
                        },
                        {
                            "id": "80917",
                            "fecha": "2025-09-08 15:30:00",
                            "nombre": "Villa Dalmine vs. Liniers",
                            "horaDia": 2,
                            "canales": [
                                {
                                    "id": "50",
                                    "nombre": "TYC SPORTS PLAY"
                                }
                            ],
                            "deporte": {
                                "id": "1",
                                "nombre": "Fútbol",
                                "icono": "futbol.png"
                            }
                        },
                        {
                            "id": "80918",
                            "fecha": "2025-09-08 15:30:00",
                            "nombre": "Flandria vs. Deportivo Laferrere",
                            "horaDia": 2,
                            "canales": [
                                {
                                    "id": "50",
                                    "nombre": "TYC SPORTS PLAY"
                                }
                            ],
                            "deporte": {
                                "id": "1",
                                "nombre": "Fútbol",
                                "icono": "futbol.png"
                            }
                        },
                        {
                            "id": "80919",
                            "fecha": "2025-09-08 18:35:00",
                            "nombre": "Brown de Adrogué vs. San Martín Burzaco",
                            "horaDia": 2,
                            "canales": [
                                {
                                    "id": "164",
                                    "nombre": "DSPORTS / DGO"
                                }
                            ],
                            "deporte": {
                                "id": "1",
                                "nombre": "Fútbol",
                                "icono": "futbol.png"
                            }
                        },
                        {
                            "id": "80920",
                            "fecha": "2025-09-08 20:00:00",
                            "nombre": "Midland vs. Sportivo Dock Sud",
                            "horaDia": 3,
                            "canales": [
                                {
                                    "id": "50",
                                    "nombre": "TYC SPORTS PLAY"
                                }
                            ],
                            "deporte": {
                                "id": "1",
                                "nombre": "Fútbol",
                                "icono": "futbol.png"
                            }
                        }
                    ],
                    "deporte": {
                        "id": "1",
                        "nombre": "Fútbol",
                        "icono": "futbol.png"
                    },
                    "primerFecha": "2025-09-08 15:30:00",
                    "cantidad_eventos": 5
                },
                {
                    "id": "254",
                    "nombre": "Primera C",
                    "eventos": [
                        {
                            "id": "80921",
                            "fecha": "2025-09-08 15:30:00",
                            "nombre": "Yupanqui vs. Victoriano Arenas",
                            "horaDia": 2,
                            "canales": [],
                            "deporte": {
                                "id": "1",
                                "nombre": "Fútbol",
                                "icono": "futbol.png"
                            }
                        },
                        {
                            "id": "80922",
                            "fecha": "2025-09-08 15:30:00",
                            "nombre": "Centro Español vs. Sportivo Barracas",
                            "horaDia": 2,
                            "canales": [],
                            "deporte": {
                                "id": "1",
                                "nombre": "Fútbol",
                                "icono": "futbol.png"
                            }
                        },
                        {
                            "id": "80923",
                            "fecha": "2025-09-08 15:30:00",
                            "nombre": "Leandro N. Alem vs. Central Córdoba (R)",
                            "horaDia": 2,
                            "canales": [],
                            "deporte": {
                                "id": "1",
                                "nombre": "Fútbol",
                                "icono": "futbol.png"
                            }
                        }
                    ],
                    "deporte": {
                        "id": "1",
                        "nombre": "Fútbol",
                        "icono": "futbol.png"
                    },
                    "primerFecha": "2025-09-08 15:30:00",
                    "cantidad_eventos": 3
                },
                {
                    "id": "1152",
                    "nombre": "Eliminatorias Europeas",
                    "eventos": [
                        {
                            "id": "80924",
                            "fecha": "2025-09-08 15:45:00",
                            "nombre": "Israel vs. Italia",
                            "horaDia": 2,
                            "canales": [
                                {
                                    "id": "171",
                                    "nombre": "DGO"
                                },
                                {
                                    "id": "181",
                                    "nombre": "DISNEY + PREMIUM "
                                },
                                {
                                    "id": "8",
                                    "nombre": "ESPN",
                                    "plataformas": [
                                        "HD",
                                        "ANALOGICO",
                                        "ISDBT",
                                        "IPTV"
                                    ],
                                    "frecuencias": {
                                        "HD": 25,
                                        "ANALOGICO": 19,
                                        "ISDBT": 25.4,
                                        "IPTV": 19
                                    }
                                }
                            ],
                            "deporte": {
                                "id": "1",
                                "nombre": "Fútbol",
                                "icono": "futbol.png"
                            }
                        },
                        {
                            "id": "80929",
                            "fecha": "2025-09-08 15:45:00",
                            "nombre": "Bielorrusia vs. Escocia",
                            "horaDia": 2,
                            "canales": [
                                {
                                    "id": "181",
                                    "nombre": "DISNEY + PREMIUM "
                                }
                            ],
                            "deporte": {
                                "id": "1",
                                "nombre": "Fútbol",
                                "icono": "futbol.png"
                            }
                        },
                        {
                            "id": "80930",
                            "fecha": "2025-09-08 15:45:00",
                            "nombre": "Croacia vs. Montenegro",
                            "horaDia": 2,
                            "canales": [
                                {
                                    "id": "181",
                                    "nombre": "DISNEY + PREMIUM "
                                }
                            ],
                            "deporte": {
                                "id": "1",
                                "nombre": "Fútbol",
                                "icono": "futbol.png"
                            }
                        },
                        {
                            "id": "80931",
                            "fecha": "2025-09-08 15:45:00",
                            "nombre": "Gibraltar vs. Islas Feroe",
                            "horaDia": 2,
                            "canales": [
                                {
                                    "id": "181",
                                    "nombre": "DISNEY + PREMIUM "
                                }
                            ],
                            "deporte": {
                                "id": "1",
                                "nombre": "Fútbol",
                                "icono": "futbol.png"
                            }
                        },
                        {
                            "id": "80932",
                            "fecha": "2025-09-08 15:45:00",
                            "nombre": "Grecia vs. Dinamarca",
                            "horaDia": 2,
                            "canales": [
                                {
                                    "id": "181",
                                    "nombre": "DISNEY + PREMIUM "
                                }
                            ],
                            "deporte": {
                                "id": "1",
                                "nombre": "Fútbol",
                                "icono": "futbol.png"
                            }
                        },
                        {
                            "id": "80933",
                            "fecha": "2025-09-08 15:45:00",
                            "nombre": "Kosovo vs. Suecia",
                            "horaDia": 2,
                            "canales": [
                                {
                                    "id": "181",
                                    "nombre": "DISNEY + PREMIUM "
                                }
                            ],
                            "deporte": {
                                "id": "1",
                                "nombre": "Fútbol",
                                "icono": "futbol.png"
                            }
                        },
                        {
                            "id": "80934",
                            "fecha": "2025-09-08 15:45:00",
                            "nombre": "Suiza vs. Eslovenia",
                            "horaDia": 2,
                            "canales": [
                                {
                                    "id": "181",
                                    "nombre": "DISNEY + PREMIUM "
                                }
                            ],
                            "deporte": {
                                "id": "1",
                                "nombre": "Fútbol",
                                "icono": "futbol.png"
                            }
                        }
                    ],
                    "deporte": {
                        "id": "1",
                        "nombre": "Fútbol",
                        "icono": "futbol.png"
                    },
                    "primerFecha": "2025-09-08 15:45:00",
                    "cantidad_eventos": 7
                },
                {
                    "id": "1659",
                    "nombre": "Segunda división de España",
                    "eventos": [
                        {
                            "id": "80925",
                            "fecha": "2025-09-08 15:30:00",
                            "nombre": "Eibar vs. Andorra",
                            "horaDia": 2,
                            "canales": [
                                {
                                    "id": "164",
                                    "nombre": "DSPORTS / DGO"
                                }
                            ],
                            "deporte": {
                                "id": "1",
                                "nombre": "Fútbol",
                                "icono": "futbol.png"
                            }
                        }
                    ],
                    "deporte": {
                        "id": "1",
                        "nombre": "Fútbol",
                        "icono": "futbol.png"
                    },
                    "primerFecha": "2025-09-08 15:30:00",
                    "cantidad_eventos": 1
                },
                {
                    "id": "368",
                    "nombre": "MLB (Major League Baseball)",
                    "eventos": [
                        {
                            "id": "80926",
                            "fecha": "2025-09-08 19:30:00",
                            "nombre": "New York Mets vs. Philadelphia Phillies",
                            "horaDia": 2,
                            "canales": [
                                {
                                    "id": "181",
                                    "nombre": "DISNEY + PREMIUM "
                                },
                                {
                                    "id": "25",
                                    "nombre": "ESPN 3",
                                    "plataformas": [
                                        "HD",
                                        "ANALOGICO",
                                        "ISDBT",
                                        "IPTV"
                                    ],
                                    "frecuencias": {
                                        "HD": 27,
                                        "ANALOGICO": 21,
                                        "ISDBT": 25.6,
                                        "IPTV": 21
                                    }
                                }
                            ],
                            "deporte": {
                                "id": "7",
                                "nombre": "Polideportivo",
                                "icono": "polideportivo.png"
                            }
                        },
                        {
                            "id": "80927",
                            "fecha": "2025-09-08 21:00:00",
                            "nombre": "Minnesota Vikings vs. Chicago Bears",
                            "horaDia": 3,
                            "canales": [
                                {
                                    "id": "181",
                                    "nombre": "DISNEY + PREMIUM "
                                },
                                {
                                    "id": "39",
                                    "nombre": "ESPN 2",
                                    "plataformas": [
                                        "HD",
                                        "ANALOGICO",
                                        "ISDBT",
                                        "IPTV"
                                    ],
                                    "frecuencias": {
                                        "HD": 26,
                                        "ANALOGICO": 20,
                                        "ISDBT": 25.5,
                                        "IPTV": 20
                                    }
                                }
                            ],
                            "deporte": {
                                "id": "7",
                                "nombre": "Polideportivo",
                                "icono": "polideportivo.png"
                            }
                        }
                    ],
                    "deporte": {
                        "id": "7",
                        "nombre": "Polideportivo",
                        "icono": "polideportivo.png"
                    },
                    "primerFecha": "2025-09-08 19:30:00",
                    "cantidad_eventos": 2
                }
            ],
            "eventos": [],
            "tieneEventos": true
        },
        {
            "fecha": "2025-09-09",
            "torneos": [
                {
                    "id": "1633",
                    "nombre": "Eliminatorias Sudamericanas",
                    "eventos": [
                        {
                            "id": "80939",
                            "fecha": "2025-09-09 20:00:00",
                            "nombre": "Ecuador vs. Argentina",
                            "horaDia": 3,
                            "canales": [
                                {
                                    "id": "158",
                                    "nombre": "TELEFE"
                                },
                                {
                                    "id": "20",
                                    "nombre": "TYC SPORTS",
                                    "plataformas": [
                                        "HD",
                                        "ANALOGICO",
                                        "ISDBT",
                                        "IPTV"
                                    ],
                                    "frecuencias": {
                                        "HD": 23,
                                        "ANALOGICO": 17,
                                        "ISDBT": 24.5,
                                        "IPTV": 17
                                    }
                                }
                            ],
                            "deporte": {
                                "id": "1",
                                "nombre": "Fútbol",
                                "icono": "futbol.png"
                            }
                        },
                        {
                            "id": "80940",
                            "fecha": "2025-09-09 20:30:00",
                            "nombre": "Venezuela vs. Colombia",
                            "horaDia": 3,
                            "canales": [
                                {
                                    "id": "164",
                                    "nombre": "DSPORTS / DGO"
                                }
                            ],
                            "deporte": {
                                "id": "1",
                                "nombre": "Fútbol",
                                "icono": "futbol.png"
                            }
                        },
                        {
                            "id": "80941",
                            "fecha": "2025-09-09 20:30:00",
                            "nombre": "Perú vs. Paraguay",
                            "horaDia": 3,
                            "canales": [
                                {
                                    "id": "16",
                                    "nombre": "DSPORTS 2 / DGO"
                                }
                            ],
                            "deporte": {
                                "id": "1",
                                "nombre": "Fútbol",
                                "icono": "futbol.png"
                            }
                        },
                        {
                            "id": "80942",
                            "fecha": "2025-09-09 20:30:00",
                            "nombre": "Bolivia vs. Brasil",
                            "horaDia": 3,
                            "canales": [
                                {
                                    "id": "50",
                                    "nombre": "TYC SPORTS PLAY"
                                }
                            ],
                            "deporte": {
                                "id": "1",
                                "nombre": "Fútbol",
                                "icono": "futbol.png"
                            }
                        },
                        {
                            "id": "80943",
                            "fecha": "2025-09-09 20:30:00",
                            "nombre": "Chile vs. Uruguay",
                            "horaDia": 3,
                            "canales": [
                                {
                                    "id": "50",
                                    "nombre": "TYC SPORTS PLAY"
                                }
                            ],
                            "deporte": {
                                "id": "1",
                                "nombre": "Fútbol",
                                "icono": "futbol.png"
                            }
                        }
                    ],
                    "deporte": {
                        "id": "1",
                        "nombre": "Fútbol",
                        "icono": "futbol.png"
                    },
                    "primerFecha": "2025-09-09 20:00:00",
                    "cantidad_eventos": 5
                },
                {
                    "id": "838",
                    "nombre": "Amistoso Internacional",
                    "eventos": [
                        {
                            "id": "80947",
                            "fecha": "2025-09-09 13:00:00",
                            "nombre": "Estonia vs. Andorra",
                            "horaDia": 2,
                            "canales": [
                                {
                                    "id": "181",
                                    "nombre": "DISNEY + PREMIUM "
                                }
                            ],
                            "deporte": {
                                "id": "1",
                                "nombre": "Fútbol",
                                "icono": "futbol.png"
                            }
                        }
                    ],
                    "deporte": {
                        "id": "1",
                        "nombre": "Fútbol",
                        "icono": "futbol.png"
                    },
                    "primerFecha": "2025-09-09 13:00:00",
                    "cantidad_eventos": 1
                },
                {
                    "id": "1152",
                    "nombre": "Eliminatorias Europeas",
                    "eventos": [
                        {
                            "id": "80944",
                            "fecha": "2025-09-09 13:00:00",
                            "nombre": "Azerbaiyán vs. Ucrania",
                            "horaDia": 2,
                            "canales": [
                                {
                                    "id": "171",
                                    "nombre": "DGO"
                                },
                                {
                                    "id": "39",
                                    "nombre": "ESPN 2",
                                    "plataformas": [
                                        "HD",
                                        "ANALOGICO",
                                        "ISDBT",
                                        "IPTV"
                                    ],
                                    "frecuencias": {
                                        "HD": 26,
                                        "ANALOGICO": 20,
                                        "ISDBT": 25.5,
                                        "IPTV": 20
                                    }
                                }
                            ],
                            "deporte": {
                                "id": "1",
                                "nombre": "Fútbol",
                                "icono": "futbol.png"
                            }
                        },
                        {
                            "id": "80948",
                            "fecha": "2025-09-09 13:00:00",
                            "nombre": "Armenia vs. Irlanda",
                            "horaDia": 2,
                            "canales": [
                                {
                                    "id": "181",
                                    "nombre": "DISNEY + PREMIUM "
                                }
                            ],
                            "deporte": {
                                "id": "1",
                                "nombre": "Fútbol",
                                "icono": "futbol.png"
                            }
                        },
                        {
                            "id": "80949",
                            "fecha": "2025-09-09 15:30:00",
                            "nombre": "Noruega vs. Moldavia",
                            "horaDia": 2,
                            "canales": [
                                {
                                    "id": "181",
                                    "nombre": "DISNEY + PREMIUM "
                                }
                            ],
                            "deporte": {
                                "id": "1",
                                "nombre": "Fútbol",
                                "icono": "futbol.png"
                            }
                        },
                        {
                            "id": "80945",
                            "fecha": "2025-09-09 15:45:00",
                            "nombre": "Serbia vs. Inglaterra",
                            "horaDia": 2,
                            "canales": [
                                {
                                    "id": "171",
                                    "nombre": "DGO"
                                },
                                {
                                    "id": "181",
                                    "nombre": "DISNEY + PREMIUM "
                                },
                                {
                                    "id": "8",
                                    "nombre": "ESPN",
                                    "plataformas": [
                                        "HD",
                                        "ANALOGICO",
                                        "ISDBT",
                                        "IPTV"
                                    ],
                                    "frecuencias": {
                                        "HD": 25,
                                        "ANALOGICO": 19,
                                        "ISDBT": 25.4,
                                        "IPTV": 19
                                    }
                                }
                            ],
                            "deporte": {
                                "id": "1",
                                "nombre": "Fútbol",
                                "icono": "futbol.png"
                            }
                        },
                        {
                            "id": "80950",
                            "fecha": "2025-09-09 15:45:00",
                            "nombre": "Albania vs. Letonia",
                            "horaDia": 2,
                            "canales": [
                                {
                                    "id": "181",
                                    "nombre": "DISNEY + PREMIUM "
                                }
                            ],
                            "deporte": {
                                "id": "1",
                                "nombre": "Fútbol",
                                "icono": "futbol.png"
                            }
                        },
                        {
                            "id": "80951",
                            "fecha": "2025-09-09 15:45:00",
                            "nombre": "Bosnia-Herzegovina vs. Austria",
                            "horaDia": 2,
                            "canales": [
                                {
                                    "id": "181",
                                    "nombre": "DISNEY + PREMIUM "
                                }
                            ],
                            "deporte": {
                                "id": "1",
                                "nombre": "Fútbol",
                                "icono": "futbol.png"
                            }
                        },
                        {
                            "id": "80952",
                            "fecha": "2025-09-09 15:45:00",
                            "nombre": "Chipre vs. Rumania",
                            "horaDia": 2,
                            "canales": [
                                {
                                    "id": "181",
                                    "nombre": "DISNEY + PREMIUM "
                                }
                            ],
                            "deporte": {
                                "id": "1",
                                "nombre": "Fútbol",
                                "icono": "futbol.png"
                            }
                        },
                        {
                            "id": "80953",
                            "fecha": "2025-09-09 15:45:00",
                            "nombre": "Francia vs. Islandia",
                            "horaDia": 2,
                            "canales": [
                                {
                                    "id": "181",
                                    "nombre": "DISNEY + PREMIUM "
                                }
                            ],
                            "deporte": {
                                "id": "1",
                                "nombre": "Fútbol",
                                "icono": "futbol.png"
                            }
                        },
                        {
                            "id": "80954",
                            "fecha": "2025-09-09 15:45:00",
                            "nombre": "Hungría vs. Portugal",
                            "horaDia": 2,
                            "canales": [
                                {
                                    "id": "181",
                                    "nombre": "DISNEY + PREMIUM "
                                }
                            ],
                            "deporte": {
                                "id": "1",
                                "nombre": "Fútbol",
                                "icono": "futbol.png"
                            }
                        }
                    ],
                    "deporte": {
                        "id": "1",
                        "nombre": "Fútbol",
                        "icono": "futbol.png"
                    },
                    "primerFecha": "2025-09-09 13:00:00",
                    "cantidad_eventos": 9
                },
                {
                    "id": "254",
                    "nombre": "Primera C",
                    "eventos": [
                        {
                            "id": "80935",
                            "fecha": "2025-09-09 15:30:00",
                            "nombre": "Claypole vs. Deportivo Español",
                            "horaDia": 2,
                            "canales": [],
                            "deporte": {
                                "id": "1",
                                "nombre": "Fútbol",
                                "icono": "futbol.png"
                            }
                        },
                        {
                            "id": "80936",
                            "fecha": "2025-09-09 15:30:00",
                            "nombre": "Club Luján vs. Deportivo Paraguayo",
                            "horaDia": 2,
                            "canales": [],
                            "deporte": {
                                "id": "1",
                                "nombre": "Fútbol",
                                "icono": "futbol.png"
                            }
                        },
                        {
                            "id": "80937",
                            "fecha": "2025-09-09 15:30:00",
                            "nombre": "Juventud Unida (SM) vs. Central Ballester",
                            "horaDia": 2,
                            "canales": [],
                            "deporte": {
                                "id": "1",
                                "nombre": "Fútbol",
                                "icono": "futbol.png"
                            }
                        },
                        {
                            "id": "80938",
                            "fecha": "2025-09-09 15:30:00",
                            "nombre": "Camioneros vs. Cañuelas",
                            "horaDia": 2,
                            "canales": [],
                            "deporte": {
                                "id": "1",
                                "nombre": "Fútbol",
                                "icono": "futbol.png"
                            }
                        }
                    ],
                    "deporte": {
                        "id": "1",
                        "nombre": "Fútbol",
                        "icono": "futbol.png"
                    },
                    "primerFecha": "2025-09-09 15:30:00",
                    "cantidad_eventos": 4
                },
                {
                    "id": "21",
                    "nombre": "Amistoso",
                    "eventos": [
                        {
                            "id": "80955",
                            "fecha": "2025-09-09 15:45:00",
                            "nombre": "Gales vs. Canadá",
                            "horaDia": 2,
                            "canales": [
                                {
                                    "id": "181",
                                    "nombre": "DISNEY + PREMIUM "
                                }
                            ],
                            "deporte": {
                                "id": "1",
                                "nombre": "Fútbol",
                                "icono": "futbol.png"
                            }
                        }
                    ],
                    "deporte": {
                        "id": "1",
                        "nombre": "Fútbol",
                        "icono": "futbol.png"
                    },
                    "primerFecha": "2025-09-09 15:45:00",
                    "cantidad_eventos": 1
                },
                {
                    "id": "347",
                    "nombre": "Reserva",
                    "eventos": [
                        {
                            "id": "80946",
                            "fecha": "2025-09-09 14:45:00",
                            "nombre": "Estudiantes LP vs. Defensa y Justicia",
                            "horaDia": 2,
                            "canales": [
                                {
                                    "id": "181",
                                    "nombre": "DISNEY + PREMIUM "
                                },
                                {
                                    "id": "25",
                                    "nombre": "ESPN 3",
                                    "plataformas": [
                                        "HD",
                                        "ANALOGICO",
                                        "ISDBT",
                                        "IPTV"
                                    ],
                                    "frecuencias": {
                                        "HD": 27,
                                        "ANALOGICO": 21,
                                        "ISDBT": 25.6,
                                        "IPTV": 21
                                    }
                                }
                            ],
                            "deporte": {
                                "id": "1",
                                "nombre": "Fútbol",
                                "icono": "futbol.png"
                            }
                        }
                    ],
                    "deporte": {
                        "id": "1",
                        "nombre": "Fútbol",
                        "icono": "futbol.png"
                    },
                    "primerFecha": "2025-09-09 14:45:00",
                    "cantidad_eventos": 1
                },
                {
                    "id": "144",
                    "nombre": "WNBA",
                    "eventos": [
                        {
                            "id": "80956",
                            "fecha": "2025-09-09 20:30:00",
                            "nombre": "Minnesota Lynx vs. Indiana Fever",
                            "horaDia": 3,
                            "canales": [
                                {
                                    "id": "39",
                                    "nombre": "ESPN 2",
                                    "plataformas": [
                                        "HD",
                                        "ANALOGICO",
                                        "ISDBT",
                                        "IPTV"
                                    ],
                                    "frecuencias": {
                                        "HD": 26,
                                        "ANALOGICO": 20,
                                        "ISDBT": 25.5,
                                        "IPTV": 20
                                    }
                                }
                            ],
                            "deporte": {
                                "id": "2",
                                "nombre": "Básquet",
                                "icono": "basquet.png"
                            }
                        }
                    ],
                    "deporte": {
                        "id": "2",
                        "nombre": "Básquet",
                        "icono": "basquet.png"
                    },
                    "primerFecha": "2025-09-09 20:30:00",
                    "cantidad_eventos": 1
                },
                {
                    "id": "730",
                    "nombre": "Eurobasket",
                    "eventos": [
                        {
                            "id": "80957",
                            "fecha": "2025-09-09 10:00:00",
                            "nombre": "Cuartos de Final",
                            "horaDia": 1,
                            "canales": [
                                {
                                    "id": "164",
                                    "nombre": "DSPORTS / DGO"
                                }
                            ],
                            "deporte": {
                                "id": "2",
                                "nombre": "Básquet",
                                "icono": "basquet.png"
                            }
                        },
                        {
                            "id": "80958",
                            "fecha": "2025-09-09 10:00:00",
                            "nombre": "Cuartos de Final",
                            "horaDia": 1,
                            "canales": [
                                {
                                    "id": "16",
                                    "nombre": "DSPORTS 2 / DGO"
                                }
                            ],
                            "deporte": {
                                "id": "2",
                                "nombre": "Básquet",
                                "icono": "basquet.png"
                            }
                        }
                    ],
                    "deporte": {
                        "id": "2",
                        "nombre": "Básquet",
                        "icono": "basquet.png"
                    },
                    "primerFecha": "2025-09-09 10:00:00",
                    "cantidad_eventos": 2
                },
                {
                    "id": "1321",
                    "nombre": "Ciclismo ",
                    "eventos": [
                        {
                            "id": "80959",
                            "fecha": "2025-09-09 10:00:00",
                            "nombre": "UCI Montain Bike Championships 2025",
                            "horaDia": 1,
                            "canales": [
                                {
                                    "id": "185",
                                    "nombre": "DSPORTS + / DGO",
                                    "plataformas": [
                                        "HD",
                                        "ANALOGICO",
                                        "ISDBT",
                                        "IPTV"
                                    ]
                                }
                            ],
                            "deporte": {
                                "id": "7",
                                "nombre": "Polideportivo",
                                "icono": "polideportivo.png"
                            }
                        }
                    ],
                    "deporte": {
                        "id": "7",
                        "nombre": "Polideportivo",
                        "icono": "polideportivo.png"
                    },
                    "primerFecha": "2025-09-09 10:00:00",
                    "cantidad_eventos": 1
                },
                {
                    "id": "513",
                    "nombre": "Ciclismo - Vuelta de España",
                    "eventos": [
                        {
                            "id": "80960",
                            "fecha": "2025-09-09 10:50:00",
                            "nombre": "Etapa 16",
                            "horaDia": 1,
                            "canales": [
                                {
                                    "id": "181",
                                    "nombre": "DISNEY + PREMIUM "
                                },
                                {
                                    "id": "39",
                                    "nombre": "ESPN 2",
                                    "plataformas": [
                                        "HD",
                                        "ANALOGICO",
                                        "ISDBT",
                                        "IPTV"
                                    ],
                                    "frecuencias": {
                                        "HD": 26,
                                        "ANALOGICO": 20,
                                        "ISDBT": 25.5,
                                        "IPTV": 20
                                    }
                                }
                            ],
                            "deporte": {
                                "id": "7",
                                "nombre": "Polideportivo",
                                "icono": "polideportivo.png"
                            }
                        }
                    ],
                    "deporte": {
                        "id": "7",
                        "nombre": "Polideportivo",
                        "icono": "polideportivo.png"
                    },
                    "primerFecha": "2025-09-09 10:50:00",
                    "cantidad_eventos": 1
                }
            ],
            "eventos": [],
            "tieneEventos": true
        },
        {
            "fecha": "2025-09-10",
            "torneos": [
                {
                    "id": "254",
                    "nombre": "Primera C",
                    "eventos": [
                        {
                            "id": "81012",
                            "fecha": "2025-09-10 15:35:00",
                            "nombre": "Muniz vs. Ituzaingó",
                            "horaDia": 2,
                            "canales": [
                                {
                                    "id": "164",
                                    "nombre": "DSPORTS / DGO"
                                }
                            ],
                            "deporte": {
                                "id": "1",
                                "nombre": "Fútbol",
                                "icono": "futbol.png"
                            }
                        }
                    ],
                    "deporte": {
                        "id": "1",
                        "nombre": "Fútbol",
                        "icono": "futbol.png"
                    },
                    "primerFecha": "2025-09-10 15:35:00",
                    "cantidad_eventos": 1
                },
                {
                    "id": "1634",
                    "nombre": "Ciclismo - La Vuelta",
                    "eventos": [
                        {
                            "id": "80995",
                            "fecha": "2025-09-10 08:20:00",
                            "nombre": "Etapa #17",
                            "horaDia": 1,
                            "canales": [
                                {
                                    "id": "181",
                                    "nombre": "DISNEY + PREMIUM "
                                },
                                {
                                    "id": "39",
                                    "nombre": "ESPN 2",
                                    "plataformas": [
                                        "HD",
                                        "ANALOGICO",
                                        "ISDBT",
                                        "IPTV"
                                    ],
                                    "frecuencias": {
                                        "HD": 26,
                                        "ANALOGICO": 20,
                                        "ISDBT": 25.5,
                                        "IPTV": 20
                                    }
                                }
                            ],
                            "deporte": {
                                "id": "7",
                                "nombre": "Polideportivo",
                                "icono": "polideportivo.png"
                            }
                        }
                    ],
                    "deporte": {
                        "id": "7",
                        "nombre": "Polideportivo",
                        "icono": "polideportivo.png"
                    },
                    "primerFecha": "2025-09-10 08:20:00",
                    "cantidad_eventos": 1
                },
                {
                    "id": "730",
                    "nombre": "Eurobasket",
                    "eventos": [
                        {
                            "id": "81013",
                            "fecha": "2025-09-10 10:00:00",
                            "nombre": "Cuartos de Final",
                            "horaDia": 1,
                            "canales": [
                                {
                                    "id": "164",
                                    "nombre": "DSPORTS / DGO"
                                }
                            ],
                            "deporte": {
                                "id": "2",
                                "nombre": "Básquet",
                                "icono": "basquet.png"
                            }
                        },
                        {
                            "id": "81014",
                            "fecha": "2025-09-10 10:00:00",
                            "nombre": "Cuartos de Final",
                            "horaDia": 1,
                            "canales": [
                                {
                                    "id": "164",
                                    "nombre": "DSPORTS / DGO"
                                }
                            ],
                            "deporte": {
                                "id": "2",
                                "nombre": "Básquet",
                                "icono": "basquet.png"
                            }
                        }
                    ],
                    "deporte": {
                        "id": "2",
                        "nombre": "Básquet",
                        "icono": "basquet.png"
                    },
                    "primerFecha": "2025-09-10 10:00:00",
                    "cantidad_eventos": 2
                },
                {
                    "id": "368",
                    "nombre": "MLB (Major League Baseball)",
                    "eventos": [
                        {
                            "id": "80996",
                            "fecha": "2025-09-10 20:00:00",
                            "nombre": "Toronto Blue Jays vs. Houston Astros",
                            "horaDia": 3,
                            "canales": [
                                {
                                    "id": "181",
                                    "nombre": "DISNEY + PREMIUM "
                                },
                                {
                                    "id": "27",
                                    "nombre": "FOX SPORTS 3",
                                    "plataformas": [
                                        "HD",
                                        "ANALOGICO",
                                        "ISDBT",
                                        "IPTV"
                                    ],
                                    "frecuencias": {
                                        "HD": 22,
                                        "ANALOGICO": 16,
                                        "ISDBT": 24.4,
                                        "IPTV": 16
                                    }
                                }
                            ],
                            "deporte": {
                                "id": "7",
                                "nombre": "Polideportivo",
                                "icono": "polideportivo.png"
                            }
                        }
                    ],
                    "deporte": {
                        "id": "7",
                        "nombre": "Polideportivo",
                        "icono": "polideportivo.png"
                    },
                    "primerFecha": "2025-09-10 20:00:00",
                    "cantidad_eventos": 1
                }
            ],
            "eventos": [],
            "tieneEventos": true
        },
        {
            "fecha": "2025-09-11",
            "torneos": [
                {
                    "id": "1346",
                    "nombre": "Liga Profesional Argentina",
                    "eventos": [
                        {
                            "id": "80997",
                            "fecha": "2025-09-11 19:45:00",
                            "nombre": "Belgrano vs. San Martin SJ",
                            "horaDia": 2,
                            "canales": [
                                {
                                    "id": "181",
                                    "nombre": "DISNEY + PREMIUM "
                                },
                                {
                                    "id": "8",
                                    "nombre": "ESPN",
                                    "plataformas": [
                                        "HD",
                                        "ANALOGICO",
                                        "ISDBT",
                                        "IPTV"
                                    ],
                                    "frecuencias": {
                                        "HD": 25,
                                        "ANALOGICO": 19,
                                        "ISDBT": 25.4,
                                        "IPTV": 19
                                    }
                                }
                            ],
                            "deporte": {
                                "id": "1",
                                "nombre": "Fútbol",
                                "icono": "futbol.png"
                            }
                        }
                    ],
                    "deporte": {
                        "id": "1",
                        "nombre": "Fútbol",
                        "icono": "futbol.png"
                    },
                    "primerFecha": "2025-09-11 19:45:00",
                    "cantidad_eventos": 1
                },
                {
                    "id": "347",
                    "nombre": "Reserva",
                    "eventos": [
                        {
                            "id": "80998",
                            "fecha": "2025-09-11 14:45:00",
                            "nombre": "Huracán vs. Racing Club",
                            "horaDia": 2,
                            "canales": [
                                {
                                    "id": "181",
                                    "nombre": "DISNEY + PREMIUM "
                                },
                                {
                                    "id": "39",
                                    "nombre": "ESPN 2",
                                    "plataformas": [
                                        "HD",
                                        "ANALOGICO",
                                        "ISDBT",
                                        "IPTV"
                                    ],
                                    "frecuencias": {
                                        "HD": 26,
                                        "ANALOGICO": 20,
                                        "ISDBT": 25.5,
                                        "IPTV": 20
                                    }
                                }
                            ],
                            "deporte": {
                                "id": "1",
                                "nombre": "Fútbol",
                                "icono": "futbol.png"
                            }
                        }
                    ],
                    "deporte": {
                        "id": "1",
                        "nombre": "Fútbol",
                        "icono": "futbol.png"
                    },
                    "primerFecha": "2025-09-11 14:45:00",
                    "cantidad_eventos": 1
                },
                {
                    "id": "142",
                    "nombre": "NFL (Fútbol Americano)",
                    "eventos": [
                        {
                            "id": "80999",
                            "fecha": "2025-09-11 21:00:00",
                            "nombre": "Green Bay Packers vs. Washington Commanders",
                            "horaDia": 3,
                            "canales": [
                                {
                                    "id": "181",
                                    "nombre": "DISNEY + PREMIUM "
                                },
                                {
                                    "id": "15",
                                    "nombre": "FOX SPORTS 2",
                                    "plataformas": [
                                        "HD",
                                        "ANALOGICO",
                                        "ISDBT",
                                        "IPTV"
                                    ],
                                    "frecuencias": {
                                        "HD": 21,
                                        "ANALOGICO": 15,
                                        "ISDBT": 24.3,
                                        "IPTV": 15
                                    }
                                }
                            ],
                            "deporte": {
                                "id": "7",
                                "nombre": "Polideportivo",
                                "icono": "polideportivo.png"
                            }
                        }
                    ],
                    "deporte": {
                        "id": "7",
                        "nombre": "Polideportivo",
                        "icono": "polideportivo.png"
                    },
                    "primerFecha": "2025-09-11 21:00:00",
                    "cantidad_eventos": 1
                },
                {
                    "id": "1634",
                    "nombre": "Ciclismo - La Vuelta",
                    "eventos": [
                        {
                            "id": "81001",
                            "fecha": "2025-09-11 10:50:00",
                            "nombre": "Etapa #18",
                            "horaDia": 1,
                            "canales": [
                                {
                                    "id": "181",
                                    "nombre": "DISNEY + PREMIUM "
                                },
                                {
                                    "id": "39",
                                    "nombre": "ESPN 2",
                                    "plataformas": [
                                        "HD",
                                        "ANALOGICO",
                                        "ISDBT",
                                        "IPTV"
                                    ],
                                    "frecuencias": {
                                        "HD": 26,
                                        "ANALOGICO": 20,
                                        "ISDBT": 25.5,
                                        "IPTV": 20
                                    }
                                }
                            ],
                            "deporte": {
                                "id": "7",
                                "nombre": "Polideportivo",
                                "icono": "polideportivo.png"
                            }
                        }
                    ],
                    "deporte": {
                        "id": "7",
                        "nombre": "Polideportivo",
                        "icono": "polideportivo.png"
                    },
                    "primerFecha": "2025-09-11 10:50:00",
                    "cantidad_eventos": 1
                },
                {
                    "id": "1236",
                    "nombre": "Golf: BMW Championship",
                    "eventos": [
                        {
                            "id": "81000",
                            "fecha": "2025-09-11 08:00:00",
                            "nombre": "Primera Vuelta",
                            "horaDia": 1,
                            "canales": [
                                {
                                    "id": "181",
                                    "nombre": "DISNEY + PREMIUM "
                                },
                                {
                                    "id": "25",
                                    "nombre": "ESPN 3",
                                    "plataformas": [
                                        "HD",
                                        "ANALOGICO",
                                        "ISDBT",
                                        "IPTV"
                                    ],
                                    "frecuencias": {
                                        "HD": 27,
                                        "ANALOGICO": 21,
                                        "ISDBT": 25.6,
                                        "IPTV": 21
                                    }
                                }
                            ],
                            "deporte": {
                                "id": "7",
                                "nombre": "Polideportivo",
                                "icono": "polideportivo.png"
                            }
                        }
                    ],
                    "deporte": {
                        "id": "7",
                        "nombre": "Polideportivo",
                        "icono": "polideportivo.png"
                    },
                    "primerFecha": "2025-09-11 08:00:00",
                    "cantidad_eventos": 1
                },
                {
                    "id": "368",
                    "nombre": "MLB (Major League Baseball)",
                    "eventos": [
                        {
                            "id": "81002",
                            "fecha": "2025-09-11 20:00:00",
                            "nombre": "New York Yankees vs. Detroit Tigers",
                            "horaDia": 3,
                            "canales": [
                                {
                                    "id": "181",
                                    "nombre": "DISNEY + PREMIUM "
                                },
                                {
                                    "id": "27",
                                    "nombre": "FOX SPORTS 3",
                                    "plataformas": [
                                        "HD",
                                        "ANALOGICO",
                                        "ISDBT",
                                        "IPTV"
                                    ],
                                    "frecuencias": {
                                        "HD": 22,
                                        "ANALOGICO": 16,
                                        "ISDBT": 24.4,
                                        "IPTV": 16
                                    }
                                }
                            ],
                            "deporte": {
                                "id": "7",
                                "nombre": "Polideportivo",
                                "icono": "polideportivo.png"
                            }
                        }
                    ],
                    "deporte": {
                        "id": "7",
                        "nombre": "Polideportivo",
                        "icono": "polideportivo.png"
                    },
                    "primerFecha": "2025-09-11 20:00:00",
                    "cantidad_eventos": 1
                }
            ],
            "eventos": [],
            "tieneEventos": true
        }
    ],
    "canales": [
        {
            "id": "171",
            "nombre": "DGO"
        },
        {
            "id": "181",
            "nombre": "DISNEY + PREMIUM "
        },
        {
            "id": "185",
            "nombre": "DSPORTS + / DGO",
            "plataformas": [
                "HD",
                "ANALOGICO",
                "ISDBT",
                "IPTV"
            ]
        },
        {
            "id": "164",
            "nombre": "DSPORTS / DGO"
        },
        {
            "id": "16",
            "nombre": "DSPORTS 2 / DGO"
        },
        {
            "id": "8",
            "nombre": "ESPN",
            "plataformas": [
                "HD",
                "ANALOGICO",
                "ISDBT",
                "IPTV"
            ],
            "frecuencias": {
                "HD": 25,
                "ANALOGICO": 19,
                "ISDBT": 25.4,
                "IPTV": 19
            }
        },
        {
            "id": "39",
            "nombre": "ESPN 2",
            "plataformas": [
                "HD",
                "ANALOGICO",
                "ISDBT",
                "IPTV"
            ],
            "frecuencias": {
                "HD": 26,
                "ANALOGICO": 20,
                "ISDBT": 25.5,
                "IPTV": 20
            }
        },
        {
            "id": "25",
            "nombre": "ESPN 3",
            "plataformas": [
                "HD",
                "ANALOGICO",
                "ISDBT",
                "IPTV"
            ],
            "frecuencias": {
                "HD": 27,
                "ANALOGICO": 21,
                "ISDBT": 25.6,
                "IPTV": 21
            }
        },
        {
            "id": "15",
            "nombre": "FOX SPORTS 2",
            "plataformas": [
                "HD",
                "ANALOGICO",
                "ISDBT",
                "IPTV"
            ],
            "frecuencias": {
                "HD": 21,
                "ANALOGICO": 15,
                "ISDBT": 24.3,
                "IPTV": 15
            }
        },
        {
            "id": "27",
            "nombre": "FOX SPORTS 3",
            "plataformas": [
                "HD",
                "ANALOGICO",
                "ISDBT",
                "IPTV"
            ],
            "frecuencias": {
                "HD": 22,
                "ANALOGICO": 16,
                "ISDBT": 24.4,
                "IPTV": 16
            }
        },
        {
            "id": "158",
            "nombre": "TELEFE"
        },
        {
            "id": "20",
            "nombre": "TYC SPORTS",
            "plataformas": [
                "HD",
                "ANALOGICO",
                "ISDBT",
                "IPTV"
            ],
            "frecuencias": {
                "HD": 23,
                "ANALOGICO": 17,
                "ISDBT": 24.5,
                "IPTV": 17
            }
        },
        {
            "id": "50",
            "nombre": "TYC SPORTS PLAY"
        }
    ],
    "hoy": "2025-09-08",
    "firma": {
        "mail": "leandromanna@gmail.com // https://mannaleandro.netlify.app/",
        "nombre": "Leandro A. Manna"
    }
}