{
    "fechas": [
        {
            "fecha": "2025-03-26",
            "torneos": [
                {
                    "id": "14",
                    "nombre": "Copa Argentina",
                    "eventos": [
                        {
                            "id": "76778",
                            "fecha": "2025-03-26 17:00:00",
                            "nombre": "San Martín de San Juan vs. Gimnasia (J)",
                            "horaDia": 2,
                            "canales": [
                                {
                                    "id": "171",
                                    "nombre": "DGO"
                                },
                                {
                                    "id": "20",
                                    "nombre": "TYC SPORTS",
                                    "plataformas": [
                                        "HD",
                                        "ANALOGICO",
                                        "ISDBT",
                                        "IPTV"
                                    ],
                                    "frecuencias": {
                                        "HD": 23,
                                        "ANALOGICO": 17,
                                        "ISDBT": 24.5,
                                        "IPTV": 17
                                    }
                                }
                            ],
                            "deporte": {
                                "id": "1",
                                "nombre": "Fútbol",
                                "icono": "futbol.png"
                            }
                        }
                    ],
                    "deporte": {
                        "id": "1",
                        "nombre": "Fútbol",
                        "icono": "futbol.png"
                    },
                    "primerFecha": "2025-03-26 17:00:00",
                    "cantidad_eventos": 1
                },
                {
                    "id": "6",
                    "nombre": "Primera Nacional",
                    "eventos": [
                        {
                            "id": "76789",
                            "fecha": "2025-03-26 21:00:00",
                            "nombre": "Quilmes vs. Colegiales (Fecha 7)",
                            "horaDia": 3,
                            "canales": [
                                {
                                    "id": "171",
                                    "nombre": "DGO"
                                },
                                {
                                    "id": "20",
                                    "nombre": "TYC SPORTS",
                                    "plataformas": [
                                        "HD",
                                        "ANALOGICO",
                                        "ISDBT",
                                        "IPTV"
                                    ],
                                    "frecuencias": {
                                        "HD": 23,
                                        "ANALOGICO": 17,
                                        "ISDBT": 24.5,
                                        "IPTV": 17
                                    }
                                }
                            ],
                            "deporte": {
                                "id": "1",
                                "nombre": "Fútbol",
                                "icono": "futbol.png"
                            }
                        }
                    ],
                    "deporte": {
                        "id": "1",
                        "nombre": "Fútbol",
                        "icono": "futbol.png"
                    },
                    "primerFecha": "2025-03-26 21:00:00",
                    "cantidad_eventos": 1
                },
                {
                    "id": "1479",
                    "nombre": "Masters 1000 de Miami",
                    "eventos": [
                        {
                            "id": "76748",
                            "fecha": "2025-03-26 14:00:00",
                            "nombre": "4tos de Final Femenino",
                            "horaDia": 2,
                            "canales": [
                                {
                                    "id": "171",
                                    "nombre": "DGO"
                                },
                                {
                                    "id": "179",
                                    "nombre": "DISNEY +"
                                },
                                {
                                    "id": "25",
                                    "nombre": "ESPN 3",
                                    "plataformas": [
                                        "HD",
                                        "ANALOGICO",
                                        "ISDBT",
                                        "IPTV"
                                    ],
                                    "frecuencias": {
                                        "HD": 27,
                                        "ANALOGICO": 21,
                                        "ISDBT": 25.6,
                                        "IPTV": 21
                                    }
                                }
                            ],
                            "deporte": {
                                "id": "3",
                                "nombre": "Tenis",
                                "icono": "tenis.png"
                            }
                        },
                        {
                            "id": "76750",
                            "fecha": "2025-03-26 16:00:00",
                            "nombre": "4tos de Final Femenino",
                            "horaDia": 2,
                            "canales": [
                                {
                                    "id": "171",
                                    "nombre": "DGO"
                                },
                                {
                                    "id": "179",
                                    "nombre": "DISNEY +"
                                },
                                {
                                    "id": "25",
                                    "nombre": "ESPN 3",
                                    "plataformas": [
                                        "HD",
                                        "ANALOGICO",
                                        "ISDBT",
                                        "IPTV"
                                    ],
                                    "frecuencias": {
                                        "HD": 27,
                                        "ANALOGICO": 21,
                                        "ISDBT": 25.6,
                                        "IPTV": 21
                                    }
                                }
                            ],
                            "deporte": {
                                "id": "3",
                                "nombre": "Tenis",
                                "icono": "tenis.png"
                            }
                        },
                        {
                            "id": "76751",
                            "fecha": "2025-03-26 20:00:00",
                            "nombre": "4tos de Final Femenino",
                            "horaDia": 3,
                            "canales": [
                                {
                                    "id": "171",
                                    "nombre": "DGO"
                                },
                                {
                                    "id": "179",
                                    "nombre": "DISNEY +"
                                },
                                {
                                    "id": "25",
                                    "nombre": "ESPN 3",
                                    "plataformas": [
                                        "HD",
                                        "ANALOGICO",
                                        "ISDBT",
                                        "IPTV"
                                    ],
                                    "frecuencias": {
                                        "HD": 27,
                                        "ANALOGICO": 21,
                                        "ISDBT": 25.6,
                                        "IPTV": 21
                                    }
                                }
                            ],
                            "deporte": {
                                "id": "3",
                                "nombre": "Tenis",
                                "icono": "tenis.png"
                            }
                        },
                        {
                            "id": "76753",
                            "fecha": "2025-03-26 21:30:00",
                            "nombre": "4tos de Final Femenino",
                            "horaDia": 3,
                            "canales": [
                                {
                                    "id": "171",
                                    "nombre": "DGO"
                                },
                                {
                                    "id": "179",
                                    "nombre": "DISNEY +"
                                },
                                {
                                    "id": "25",
                                    "nombre": "ESPN 3",
                                    "plataformas": [
                                        "HD",
                                        "ANALOGICO",
                                        "ISDBT",
                                        "IPTV"
                                    ],
                                    "frecuencias": {
                                        "HD": 27,
                                        "ANALOGICO": 21,
                                        "ISDBT": 25.6,
                                        "IPTV": 21
                                    }
                                }
                            ],
                            "deporte": {
                                "id": "3",
                                "nombre": "Tenis",
                                "icono": "tenis.png"
                            }
                        }
                    ],
                    "deporte": {
                        "id": "3",
                        "nombre": "Tenis",
                        "icono": "tenis.png"
                    },
                    "primerFecha": "2025-03-26 14:00:00",
                    "cantidad_eventos": 4
                },
                {
                    "id": "254",
                    "nombre": "Primera C",
                    "eventos": [
                        {
                            "id": "76791",
                            "fecha": "2025-03-26 15:30:00",
                            "nombre": "Berazategui vs. Ituzaingó (Fecha 3)",
                            "horaDia": 2,
                            "canales": [
                                {
                                    "id": "171",
                                    "nombre": "DGO"
                                },
                                {
                                    "id": "11",
                                    "nombre": "DSPORTS"
                                }
                            ],
                            "deporte": {
                                "id": "1",
                                "nombre": "Fútbol",
                                "icono": "futbol.png"
                            }
                        }
                    ],
                    "deporte": {
                        "id": "1",
                        "nombre": "Fútbol",
                        "icono": "futbol.png"
                    },
                    "primerFecha": "2025-03-26 15:30:00",
                    "cantidad_eventos": 1
                },
                {
                    "id": "10",
                    "nombre": "NBA",
                    "eventos": [
                        {
                            "id": "76752",
                            "fecha": "2025-03-26 20:30:00",
                            "nombre": "Indiana Pacers vs. LA Lakers",
                            "horaDia": 3,
                            "canales": [
                                {
                                    "id": "171",
                                    "nombre": "DGO"
                                },
                                {
                                    "id": "181",
                                    "nombre": "DISNEY + PREMIUM "
                                },
                                {
                                    "id": "39",
                                    "nombre": "ESPN 2",
                                    "plataformas": [
                                        "HD",
                                        "ANALOGICO",
                                        "ISDBT",
                                        "IPTV"
                                    ],
                                    "frecuencias": {
                                        "HD": 26,
                                        "ANALOGICO": 20,
                                        "ISDBT": 25.5,
                                        "IPTV": 20
                                    }
                                }
                            ],
                            "deporte": {
                                "id": "2",
                                "nombre": "Básquet",
                                "icono": "basquet.png"
                            }
                        },
                        {
                            "id": "76754",
                            "fecha": "2025-03-26 23:00:00",
                            "nombre": "Phoenix Suns vs. Boston Celtics",
                            "horaDia": 3,
                            "canales": [
                                {
                                    "id": "171",
                                    "nombre": "DGO"
                                },
                                {
                                    "id": "181",
                                    "nombre": "DISNEY + PREMIUM "
                                },
                                {
                                    "id": "39",
                                    "nombre": "ESPN 2",
                                    "plataformas": [
                                        "HD",
                                        "ANALOGICO",
                                        "ISDBT",
                                        "IPTV"
                                    ],
                                    "frecuencias": {
                                        "HD": 26,
                                        "ANALOGICO": 20,
                                        "ISDBT": 25.5,
                                        "IPTV": 20
                                    }
                                }
                            ],
                            "deporte": {
                                "id": "2",
                                "nombre": "Básquet",
                                "icono": "basquet.png"
                            }
                        }
                    ],
                    "deporte": {
                        "id": "2",
                        "nombre": "Básquet",
                        "icono": "basquet.png"
                    },
                    "primerFecha": "2025-03-26 20:30:00",
                    "cantidad_eventos": 2
                },
                {
                    "id": "347",
                    "nombre": "Reserva",
                    "eventos": [
                        {
                            "id": "76749",
                            "fecha": "2025-03-26 14:45:00",
                            "nombre": " Newell´s vs. Rosario Central",
                            "horaDia": 2,
                            "canales": [
                                {
                                    "id": "181",
                                    "nombre": "DISNEY + PREMIUM "
                                }
                            ],
                            "deporte": {
                                "id": "1",
                                "nombre": "Fútbol",
                                "icono": "futbol.png"
                            }
                        }
                    ],
                    "deporte": {
                        "id": "1",
                        "nombre": "Fútbol",
                        "icono": "futbol.png"
                    },
                    "primerFecha": "2025-03-26 14:45:00",
                    "cantidad_eventos": 1
                },
                {
                    "id": "13",
                    "nombre": "Liga Nacional",
                    "eventos": [
                        {
                            "id": "76800",
                            "fecha": "2025-03-26 20:05:00",
                            "nombre": "Boca Jrs. vs. Quimsa",
                            "horaDia": 3,
                            "canales": [
                                {
                                    "id": "171",
                                    "nombre": "DGO"
                                },
                                {
                                    "id": "11",
                                    "nombre": "DSPORTS"
                                }
                            ],
                            "deporte": {
                                "id": "2",
                                "nombre": "Básquet",
                                "icono": "basquet.png"
                            }
                        }
                    ],
                    "deporte": {
                        "id": "2",
                        "nombre": "Básquet",
                        "icono": "basquet.png"
                    },
                    "primerFecha": "2025-03-26 20:05:00",
                    "cantidad_eventos": 1
                },
                {
                    "id": "1321",
                    "nombre": "Ciclismo ",
                    "eventos": [
                        {
                            "id": "76805",
                            "fecha": "2025-03-26 11:15:00",
                            "nombre": "Classic de Panne",
                            "horaDia": 1,
                            "canales": [
                                {
                                    "id": "171",
                                    "nombre": "DGO"
                                },
                                {
                                    "id": "16",
                                    "nombre": "DSPORTS 2"
                                }
                            ],
                            "deporte": {
                                "id": "7",
                                "nombre": "Polideportivo",
                                "icono": "polideportivo.png"
                            }
                        }
                    ],
                    "deporte": {
                        "id": "7",
                        "nombre": "Polideportivo",
                        "icono": "polideportivo.png"
                    },
                    "primerFecha": "2025-03-26 11:15:00",
                    "cantidad_eventos": 1
                },
                {
                    "id": "1644",
                    "nombre": "Copa América Femenina de FUTSAL",
                    "eventos": [
                        {
                            "id": "76780",
                            "fecha": "2025-03-26 13:15:00",
                            "nombre": "Colombia vs. Perú",
                            "horaDia": 2,
                            "canales": [
                                {
                                    "id": "171",
                                    "nombre": "DGO"
                                },
                                {
                                    "id": "185",
                                    "nombre": "DSPORTS +",
                                    "plataformas": [
                                        "HD",
                                        "ANALOGICO",
                                        "ISDBT",
                                        "IPTV"
                                    ]
                                }
                            ],
                            "deporte": {
                                "id": "1",
                                "nombre": "Fútbol",
                                "icono": "futbol.png"
                            }
                        },
                        {
                            "id": "76783",
                            "fecha": "2025-03-26 15:30:00",
                            "nombre": "Uruguay vs. Argentina",
                            "horaDia": 2,
                            "canales": [
                                {
                                    "id": "171",
                                    "nombre": "DGO"
                                },
                                {
                                    "id": "185",
                                    "nombre": "DSPORTS +",
                                    "plataformas": [
                                        "HD",
                                        "ANALOGICO",
                                        "ISDBT",
                                        "IPTV"
                                    ]
                                }
                            ],
                            "deporte": {
                                "id": "1",
                                "nombre": "Fútbol",
                                "icono": "futbol.png"
                            }
                        },
                        {
                            "id": "76785",
                            "fecha": "2025-03-26 17:45:00",
                            "nombre": "Venezuela vs. Ecuador",
                            "horaDia": 2,
                            "canales": [
                                {
                                    "id": "171",
                                    "nombre": "DGO"
                                },
                                {
                                    "id": "185",
                                    "nombre": "DSPORTS +",
                                    "plataformas": [
                                        "HD",
                                        "ANALOGICO",
                                        "ISDBT",
                                        "IPTV"
                                    ]
                                }
                            ],
                            "deporte": {
                                "id": "1",
                                "nombre": "Fútbol",
                                "icono": "futbol.png"
                            }
                        },
                        {
                            "id": "76787",
                            "fecha": "2025-03-26 20:00:00",
                            "nombre": "Paraguay vs. Brasil",
                            "horaDia": 3,
                            "canales": [
                                {
                                    "id": "171",
                                    "nombre": "DGO"
                                },
                                {
                                    "id": "185",
                                    "nombre": "DSPORTS +",
                                    "plataformas": [
                                        "HD",
                                        "ANALOGICO",
                                        "ISDBT",
                                        "IPTV"
                                    ]
                                }
                            ],
                            "deporte": {
                                "id": "1",
                                "nombre": "Fútbol",
                                "icono": "futbol.png"
                            }
                        }
                    ],
                    "deporte": {
                        "id": "1",
                        "nombre": "Fútbol",
                        "icono": "futbol.png"
                    },
                    "primerFecha": "2025-03-26 13:15:00",
                    "cantidad_eventos": 4
                },
                {
                    "id": "170",
                    "nombre": "Euroliga",
                    "eventos": [
                        {
                            "id": "76795",
                            "fecha": "2025-03-26 16:05:00",
                            "nombre": "Maccabi vs. Panathinaikos",
                            "horaDia": 2,
                            "canales": [
                                {
                                    "id": "171",
                                    "nombre": "DGO"
                                },
                                {
                                    "id": "16",
                                    "nombre": "DSPORTS 2"
                                }
                            ],
                            "deporte": {
                                "id": "2",
                                "nombre": "Básquet",
                                "icono": "basquet.png"
                            }
                        }
                    ],
                    "deporte": {
                        "id": "2",
                        "nombre": "Básquet",
                        "icono": "basquet.png"
                    },
                    "primerFecha": "2025-03-26 16:05:00",
                    "cantidad_eventos": 1
                }
            ],
            "eventos": [],
            "tieneEventos": true
        },
        {
            "fecha": "2025-03-27",
            "torneos": [
                {
                    "id": "1479",
                    "nombre": "Masters 1000 de Miami",
                    "eventos": [
                        {
                            "id": "76806",
                            "fecha": "2025-03-27 14:00:00",
                            "nombre": "4tos de Final",
                            "horaDia": 2,
                            "canales": [
                                {
                                    "id": "171",
                                    "nombre": "DGO"
                                },
                                {
                                    "id": "179",
                                    "nombre": "DISNEY +"
                                },
                                {
                                    "id": "25",
                                    "nombre": "ESPN 3",
                                    "plataformas": [
                                        "HD",
                                        "ANALOGICO",
                                        "ISDBT",
                                        "IPTV"
                                    ],
                                    "frecuencias": {
                                        "HD": 27,
                                        "ANALOGICO": 21,
                                        "ISDBT": 25.6,
                                        "IPTV": 21
                                    }
                                }
                            ],
                            "deporte": {
                                "id": "3",
                                "nombre": "Tenis",
                                "icono": "tenis.png"
                            }
                        },
                        {
                            "id": "76807",
                            "fecha": "2025-03-27 16:00:00",
                            "nombre": "4tos de Final",
                            "horaDia": 2,
                            "canales": [
                                {
                                    "id": "171",
                                    "nombre": "DGO"
                                },
                                {
                                    "id": "179",
                                    "nombre": "DISNEY +"
                                },
                                {
                                    "id": "25",
                                    "nombre": "ESPN 3",
                                    "plataformas": [
                                        "HD",
                                        "ANALOGICO",
                                        "ISDBT",
                                        "IPTV"
                                    ],
                                    "frecuencias": {
                                        "HD": 27,
                                        "ANALOGICO": 21,
                                        "ISDBT": 25.6,
                                        "IPTV": 21
                                    }
                                }
                            ],
                            "deporte": {
                                "id": "3",
                                "nombre": "Tenis",
                                "icono": "tenis.png"
                            }
                        },
                        {
                            "id": "76808",
                            "fecha": "2025-03-27 20:00:00",
                            "nombre": "4tos de Final",
                            "horaDia": 3,
                            "canales": [
                                {
                                    "id": "171",
                                    "nombre": "DGO"
                                },
                                {
                                    "id": "181",
                                    "nombre": "DISNEY + PREMIUM "
                                },
                                {
                                    "id": "39",
                                    "nombre": "ESPN 2",
                                    "plataformas": [
                                        "HD",
                                        "ANALOGICO",
                                        "ISDBT",
                                        "IPTV"
                                    ],
                                    "frecuencias": {
                                        "HD": 26,
                                        "ANALOGICO": 20,
                                        "ISDBT": 25.5,
                                        "IPTV": 20
                                    }
                                }
                            ],
                            "deporte": {
                                "id": "3",
                                "nombre": "Tenis",
                                "icono": "tenis.png"
                            }
                        },
                        {
                            "id": "76814",
                            "fecha": "2025-03-27 21:30:00",
                            "nombre": "4tos de Final",
                            "horaDia": 3,
                            "canales": [
                                {
                                    "id": "171",
                                    "nombre": "DGO"
                                },
                                {
                                    "id": "181",
                                    "nombre": "DISNEY + PREMIUM "
                                },
                                {
                                    "id": "39",
                                    "nombre": "ESPN 2",
                                    "plataformas": [
                                        "HD",
                                        "ANALOGICO",
                                        "ISDBT",
                                        "IPTV"
                                    ],
                                    "frecuencias": {
                                        "HD": 26,
                                        "ANALOGICO": 20,
                                        "ISDBT": 25.5,
                                        "IPTV": 20
                                    }
                                }
                            ],
                            "deporte": {
                                "id": "3",
                                "nombre": "Tenis",
                                "icono": "tenis.png"
                            }
                        }
                    ],
                    "deporte": {
                        "id": "3",
                        "nombre": "Tenis",
                        "icono": "tenis.png"
                    },
                    "primerFecha": "2025-03-27 14:00:00",
                    "cantidad_eventos": 4
                },
                {
                    "id": "13",
                    "nombre": "Liga Nacional",
                    "eventos": [
                        {
                            "id": "76824",
                            "fecha": "2025-03-27 22:00:00",
                            "nombre": "Boca vs. Riachuelo",
                            "horaDia": 3,
                            "canales": [
                                {
                                    "id": "171",
                                    "nombre": "DGO"
                                },
                                {
                                    "id": "20",
                                    "nombre": "TYC SPORTS",
                                    "plataformas": [
                                        "HD",
                                        "ANALOGICO",
                                        "ISDBT",
                                        "IPTV"
                                    ],
                                    "frecuencias": {
                                        "HD": 23,
                                        "ANALOGICO": 17,
                                        "ISDBT": 24.5,
                                        "IPTV": 17
                                    }
                                }
                            ],
                            "deporte": {
                                "id": "2",
                                "nombre": "Básquet",
                                "icono": "basquet.png"
                            }
                        }
                    ],
                    "deporte": {
                        "id": "2",
                        "nombre": "Básquet",
                        "icono": "basquet.png"
                    },
                    "primerFecha": "2025-03-27 22:00:00",
                    "cantidad_eventos": 1
                },
                {
                    "id": "1644",
                    "nombre": "Copa América Femenina de FUTSAL",
                    "eventos": [
                        {
                            "id": "76819",
                            "fecha": "2025-03-27 13:15:00",
                            "nombre": "Uruguay vs. Chile",
                            "horaDia": 2,
                            "canales": [
                                {
                                    "id": "171",
                                    "nombre": "DGO"
                                },
                                {
                                    "id": "185",
                                    "nombre": "DSPORTS +",
                                    "plataformas": [
                                        "HD",
                                        "ANALOGICO",
                                        "ISDBT",
                                        "IPTV"
                                    ]
                                }
                            ],
                            "deporte": {
                                "id": "1",
                                "nombre": "Fútbol",
                                "icono": "futbol.png"
                            }
                        },
                        {
                            "id": "76820",
                            "fecha": "2025-03-27 15:30:00",
                            "nombre": "Argentina vs. Colombia",
                            "horaDia": 2,
                            "canales": [
                                {
                                    "id": "171",
                                    "nombre": "DGO"
                                },
                                {
                                    "id": "185",
                                    "nombre": "DSPORTS +",
                                    "plataformas": [
                                        "HD",
                                        "ANALOGICO",
                                        "ISDBT",
                                        "IPTV"
                                    ]
                                }
                            ],
                            "deporte": {
                                "id": "1",
                                "nombre": "Fútbol",
                                "icono": "futbol.png"
                            }
                        },
                        {
                            "id": "76821",
                            "fecha": "2025-03-27 17:45:00",
                            "nombre": "Paraguay vs. Bolivia",
                            "horaDia": 2,
                            "canales": [
                                {
                                    "id": "171",
                                    "nombre": "DGO"
                                },
                                {
                                    "id": "185",
                                    "nombre": "DSPORTS +",
                                    "plataformas": [
                                        "HD",
                                        "ANALOGICO",
                                        "ISDBT",
                                        "IPTV"
                                    ]
                                }
                            ],
                            "deporte": {
                                "id": "1",
                                "nombre": "Fútbol",
                                "icono": "futbol.png"
                            }
                        },
                        {
                            "id": "76822",
                            "fecha": "2025-03-27 20:00:00",
                            "nombre": "Brasil vs. Venezuela",
                            "horaDia": 3,
                            "canales": [
                                {
                                    "id": "171",
                                    "nombre": "DGO"
                                },
                                {
                                    "id": "185",
                                    "nombre": "DSPORTS +",
                                    "plataformas": [
                                        "HD",
                                        "ANALOGICO",
                                        "ISDBT",
                                        "IPTV"
                                    ]
                                }
                            ],
                            "deporte": {
                                "id": "1",
                                "nombre": "Fútbol",
                                "icono": "futbol.png"
                            }
                        }
                    ],
                    "deporte": {
                        "id": "1",
                        "nombre": "Fútbol",
                        "icono": "futbol.png"
                    },
                    "primerFecha": "2025-03-27 13:15:00",
                    "cantidad_eventos": 4
                },
                {
                    "id": "170",
                    "nombre": "Euroliga",
                    "eventos": [
                        {
                            "id": "76823",
                            "fecha": "2025-03-27 16:30:00",
                            "nombre": "Olimpia Milano vs. Barcelona",
                            "horaDia": 2,
                            "canales": [
                                {
                                    "id": "171",
                                    "nombre": "DGO"
                                },
                                {
                                    "id": "11",
                                    "nombre": "DSPORTS"
                                }
                            ],
                            "deporte": {
                                "id": "2",
                                "nombre": "Básquet",
                                "icono": "basquet.png"
                            }
                        }
                    ],
                    "deporte": {
                        "id": "2",
                        "nombre": "Básquet",
                        "icono": "basquet.png"
                    },
                    "primerFecha": "2025-03-27 16:30:00",
                    "cantidad_eventos": 1
                },
                {
                    "id": "570",
                    "nombre": "Sudamericano Sub-17",
                    "eventos": [
                        {
                            "id": "76817",
                            "fecha": "2025-03-27 18:30:00",
                            "nombre": "Perú vs. Paraguay",
                            "horaDia": 2,
                            "canales": [
                                {
                                    "id": "171",
                                    "nombre": "DGO"
                                },
                                {
                                    "id": "16",
                                    "nombre": "DSPORTS 2"
                                }
                            ],
                            "deporte": {
                                "id": "1",
                                "nombre": "Fútbol",
                                "icono": "futbol.png"
                            }
                        },
                        {
                            "id": "76818",
                            "fecha": "2025-03-27 21:00:00",
                            "nombre": "Colombia vs. Chile",
                            "horaDia": 3,
                            "canales": [
                                {
                                    "id": "171",
                                    "nombre": "DGO"
                                },
                                {
                                    "id": "16",
                                    "nombre": "DSPORTS 2"
                                }
                            ],
                            "deporte": {
                                "id": "1",
                                "nombre": "Fútbol",
                                "icono": "futbol.png"
                            }
                        }
                    ],
                    "deporte": {
                        "id": "1",
                        "nombre": "Fútbol",
                        "icono": "futbol.png"
                    },
                    "primerFecha": "2025-03-27 18:30:00",
                    "cantidad_eventos": 2
                },
                {
                    "id": "951",
                    "nombre": "Beisbol: MLB Partido de Pretemporada\t",
                    "eventos": [
                        {
                            "id": "76825",
                            "fecha": "2025-03-27 20:00:00",
                            "nombre": "Detroit Tigers vs. Los Angeles Dodgers",
                            "horaDia": 3,
                            "canales": [
                                {
                                    "id": "171",
                                    "nombre": "DGO"
                                },
                                {
                                    "id": "25",
                                    "nombre": "ESPN 3",
                                    "plataformas": [
                                        "HD",
                                        "ANALOGICO",
                                        "ISDBT",
                                        "IPTV"
                                    ],
                                    "frecuencias": {
                                        "HD": 27,
                                        "ANALOGICO": 21,
                                        "ISDBT": 25.6,
                                        "IPTV": 21
                                    }
                                }
                            ],
                            "deporte": {
                                "id": "7",
                                "nombre": "Polideportivo",
                                "icono": "polideportivo.png"
                            }
                        }
                    ],
                    "deporte": {
                        "id": "7",
                        "nombre": "Polideportivo",
                        "icono": "polideportivo.png"
                    },
                    "primerFecha": "2025-03-27 20:00:00",
                    "cantidad_eventos": 1
                },
                {
                    "id": "368",
                    "nombre": "MLB (Major League Baseball)",
                    "eventos": [
                        {
                            "id": "76810",
                            "fecha": "2025-03-27 20:00:00",
                            "nombre": "Los Angeles Dodgers vs. Detroit Tigers",
                            "horaDia": 3,
                            "canales": [
                                {
                                    "id": "179",
                                    "nombre": "DISNEY +"
                                },
                                {
                                    "id": "25",
                                    "nombre": "ESPN 3",
                                    "plataformas": [
                                        "HD",
                                        "ANALOGICO",
                                        "ISDBT",
                                        "IPTV"
                                    ],
                                    "frecuencias": {
                                        "HD": 27,
                                        "ANALOGICO": 21,
                                        "ISDBT": 25.6,
                                        "IPTV": 21
                                    }
                                }
                            ],
                            "deporte": {
                                "id": "7",
                                "nombre": "Polideportivo",
                                "icono": "polideportivo.png"
                            }
                        }
                    ],
                    "deporte": {
                        "id": "7",
                        "nombre": "Polideportivo",
                        "icono": "polideportivo.png"
                    },
                    "primerFecha": "2025-03-27 20:00:00",
                    "cantidad_eventos": 1
                },
                {
                    "id": "1577",
                    "nombre": "NHL (Hockey sobre hielo)",
                    "eventos": [
                        {
                            "id": "76812",
                            "fecha": "2025-03-27 20:30:00",
                            "nombre": "Minnesota Wild vs. Washington Capitals",
                            "horaDia": 3,
                            "canales": [
                                {
                                    "id": "181",
                                    "nombre": "DISNEY + PREMIUM "
                                }
                            ],
                            "deporte": {
                                "id": "7",
                                "nombre": "Polideportivo",
                                "icono": "polideportivo.png"
                            }
                        }
                    ],
                    "deporte": {
                        "id": "7",
                        "nombre": "Polideportivo",
                        "icono": "polideportivo.png"
                    },
                    "primerFecha": "2025-03-27 20:30:00",
                    "cantidad_eventos": 1
                }
            ],
            "eventos": [],
            "tieneEventos": true
        },
        {
            "fecha": "2025-03-28",
            "torneos": [
                {
                    "id": "127",
                    "nombre": "Ligue 1 de Francia",
                    "eventos": [
                        {
                            "id": "76739",
                            "fecha": "2025-03-28 16:30:00",
                            "nombre": "Racing Strasburgo vs. Olympique de Lyon",
                            "horaDia": 2,
                            "canales": [
                                {
                                    "id": "181",
                                    "nombre": "DISNEY + PREMIUM "
                                }
                            ],
                            "deporte": {
                                "id": "1",
                                "nombre": "Fútbol",
                                "icono": "futbol.png"
                            }
                        }
                    ],
                    "deporte": {
                        "id": "1",
                        "nombre": "Fútbol",
                        "icono": "futbol.png"
                    },
                    "primerFecha": "2025-03-28 16:30:00",
                    "cantidad_eventos": 1
                },
                {
                    "id": "129",
                    "nombre": "Bundesliga",
                    "eventos": [
                        {
                            "id": "76734",
                            "fecha": "2025-03-28 16:30:00",
                            "nombre": "Bayer Leverkusen vs Bochum",
                            "horaDia": 2,
                            "canales": [
                                {
                                    "id": "171",
                                    "nombre": "DGO"
                                },
                                {
                                    "id": "181",
                                    "nombre": "DISNEY + PREMIUM "
                                },
                                {
                                    "id": "39",
                                    "nombre": "ESPN 2",
                                    "plataformas": [
                                        "HD",
                                        "ANALOGICO",
                                        "ISDBT",
                                        "IPTV"
                                    ],
                                    "frecuencias": {
                                        "HD": 26,
                                        "ANALOGICO": 20,
                                        "ISDBT": 25.5,
                                        "IPTV": 20
                                    }
                                }
                            ],
                            "deporte": {
                                "id": "1",
                                "nombre": "Fútbol",
                                "icono": "futbol.png"
                            }
                        }
                    ],
                    "deporte": {
                        "id": "1",
                        "nombre": "Fútbol",
                        "icono": "futbol.png"
                    },
                    "primerFecha": "2025-03-28 16:30:00",
                    "cantidad_eventos": 1
                },
                {
                    "id": "126",
                    "nombre": "Liga de España",
                    "eventos": [
                        {
                            "id": "76768",
                            "fecha": "2025-03-28 17:00:00",
                            "nombre": "Athletic Bilbao\tvs.\tOsasuna",
                            "horaDia": 2,
                            "canales": [
                                {
                                    "id": "171",
                                    "nombre": "DGO"
                                },
                                {
                                    "id": "185",
                                    "nombre": "DSPORTS +",
                                    "plataformas": [
                                        "HD",
                                        "ANALOGICO",
                                        "ISDBT",
                                        "IPTV"
                                    ]
                                }
                            ],
                            "deporte": {
                                "id": "1",
                                "nombre": "Fútbol",
                                "icono": "futbol.png"
                            }
                        }
                    ],
                    "deporte": {
                        "id": "1",
                        "nombre": "Fútbol",
                        "icono": "futbol.png"
                    },
                    "primerFecha": "2025-03-28 17:00:00",
                    "cantidad_eventos": 1
                },
                {
                    "id": "1479",
                    "nombre": "Masters 1000 de Miami",
                    "eventos": [
                        {
                            "id": "76732",
                            "fecha": "2025-03-28 16:00:00",
                            "nombre": "Semifinal 1",
                            "horaDia": 2,
                            "canales": [
                                {
                                    "id": "171",
                                    "nombre": "DGO"
                                },
                                {
                                    "id": "179",
                                    "nombre": "DISNEY +"
                                },
                                {
                                    "id": "25",
                                    "nombre": "ESPN 3",
                                    "plataformas": [
                                        "HD",
                                        "ANALOGICO",
                                        "ISDBT",
                                        "IPTV"
                                    ],
                                    "frecuencias": {
                                        "HD": 27,
                                        "ANALOGICO": 21,
                                        "ISDBT": 25.6,
                                        "IPTV": 21
                                    }
                                }
                            ],
                            "deporte": {
                                "id": "3",
                                "nombre": "Tenis",
                                "icono": "tenis.png"
                            }
                        },
                        {
                            "id": "76733",
                            "fecha": "2025-03-28 20:00:00",
                            "nombre": "Semifinal 2",
                            "horaDia": 3,
                            "canales": [
                                {
                                    "id": "171",
                                    "nombre": "DGO"
                                },
                                {
                                    "id": "179",
                                    "nombre": "DISNEY +"
                                },
                                {
                                    "id": "25",
                                    "nombre": "ESPN 3",
                                    "plataformas": [
                                        "HD",
                                        "ANALOGICO",
                                        "ISDBT",
                                        "IPTV"
                                    ],
                                    "frecuencias": {
                                        "HD": 27,
                                        "ANALOGICO": 21,
                                        "ISDBT": 25.6,
                                        "IPTV": 21
                                    }
                                }
                            ],
                            "deporte": {
                                "id": "3",
                                "nombre": "Tenis",
                                "icono": "tenis.png"
                            }
                        }
                    ],
                    "deporte": {
                        "id": "3",
                        "nombre": "Tenis",
                        "icono": "tenis.png"
                    },
                    "primerFecha": "2025-03-28 16:00:00",
                    "cantidad_eventos": 2
                },
                {
                    "id": "13",
                    "nombre": "Liga Nacional",
                    "eventos": [
                        {
                            "id": "76738",
                            "fecha": "2025-03-28 22:00:00",
                            "nombre": "Boca vs Riachuelo",
                            "horaDia": 3,
                            "canales": [
                                {
                                    "id": "171",
                                    "nombre": "DGO"
                                },
                                {
                                    "id": "20",
                                    "nombre": "TYC SPORTS",
                                    "plataformas": [
                                        "HD",
                                        "ANALOGICO",
                                        "ISDBT",
                                        "IPTV"
                                    ],
                                    "frecuencias": {
                                        "HD": 23,
                                        "ANALOGICO": 17,
                                        "ISDBT": 24.5,
                                        "IPTV": 17
                                    }
                                },
                                {
                                    "id": "50",
                                    "nombre": "TYC SPORTS PLAY"
                                }
                            ],
                            "deporte": {
                                "id": "2",
                                "nombre": "Básquet",
                                "icono": "basquet.png"
                            }
                        }
                    ],
                    "deporte": {
                        "id": "2",
                        "nombre": "Básquet",
                        "icono": "basquet.png"
                    },
                    "primerFecha": "2025-03-28 22:00:00",
                    "cantidad_eventos": 1
                },
                {
                    "id": "1047",
                    "nombre": "EFL Championship",
                    "eventos": [
                        {
                            "id": "76735",
                            "fecha": "2025-03-28 17:00:00",
                            "nombre": "Sheffield United vs Coventry City",
                            "horaDia": 2,
                            "canales": [
                                {
                                    "id": "171",
                                    "nombre": "DGO"
                                },
                                {
                                    "id": "181",
                                    "nombre": "DISNEY + PREMIUM "
                                },
                                {
                                    "id": "7",
                                    "nombre": "FOX SPORTS",
                                    "plataformas": [
                                        "HD",
                                        "ANALOGICO",
                                        "ISDBT",
                                        "IPTV"
                                    ],
                                    "frecuencias": {
                                        "HD": 20,
                                        "ANALOGICO": 14,
                                        "ISDBT": 24.2,
                                        "IPTV": 14
                                    }
                                }
                            ],
                            "deporte": {
                                "id": "1",
                                "nombre": "Fútbol",
                                "icono": "futbol.png"
                            }
                        }
                    ],
                    "deporte": {
                        "id": "1",
                        "nombre": "Fútbol",
                        "icono": "futbol.png"
                    },
                    "primerFecha": "2025-03-28 17:00:00",
                    "cantidad_eventos": 1
                },
                {
                    "id": "233",
                    "nombre": "Voley: Liga Argentina",
                    "eventos": [
                        {
                            "id": "76737",
                            "fecha": "2025-03-28 21:00:00",
                            "nombre": "Semifinal: Ciudad vs San Lorenzo",
                            "horaDia": 3,
                            "canales": [
                                {
                                    "id": "171",
                                    "nombre": "DGO"
                                },
                                {
                                    "id": "15",
                                    "nombre": "FOX SPORTS 2",
                                    "plataformas": [
                                        "HD",
                                        "ANALOGICO",
                                        "ISDBT",
                                        "IPTV"
                                    ],
                                    "frecuencias": {
                                        "HD": 21,
                                        "ANALOGICO": 15,
                                        "ISDBT": 24.3,
                                        "IPTV": 15
                                    }
                                }
                            ],
                            "deporte": {
                                "id": "7",
                                "nombre": "Polideportivo",
                                "icono": "polideportivo.png"
                            }
                        }
                    ],
                    "deporte": {
                        "id": "7",
                        "nombre": "Polideportivo",
                        "icono": "polideportivo.png"
                    },
                    "primerFecha": "2025-03-28 21:00:00",
                    "cantidad_eventos": 1
                },
                {
                    "id": "374",
                    "nombre": "Seven de Hong Kong",
                    "eventos": [
                        {
                            "id": "76771",
                            "fecha": "2025-03-28 01:45:00",
                            "nombre": "Ventana 1",
                            "horaDia": 1,
                            "canales": [
                                {
                                    "id": "171",
                                    "nombre": "DGO"
                                },
                                {
                                    "id": "7",
                                    "nombre": "FOX SPORTS",
                                    "plataformas": [
                                        "HD",
                                        "ANALOGICO",
                                        "ISDBT",
                                        "IPTV"
                                    ],
                                    "frecuencias": {
                                        "HD": 20,
                                        "ANALOGICO": 14,
                                        "ISDBT": 24.2,
                                        "IPTV": 14
                                    }
                                }
                            ],
                            "deporte": {
                                "id": "4",
                                "nombre": "Rugby",
                                "icono": "rugby.png"
                            }
                        },
                        {
                            "id": "76772",
                            "fecha": "2025-03-28 04:55:00",
                            "nombre": "Ventana 2",
                            "horaDia": 1,
                            "canales": [
                                {
                                    "id": "171",
                                    "nombre": "DGO"
                                },
                                {
                                    "id": "7",
                                    "nombre": "FOX SPORTS",
                                    "plataformas": [
                                        "HD",
                                        "ANALOGICO",
                                        "ISDBT",
                                        "IPTV"
                                    ],
                                    "frecuencias": {
                                        "HD": 20,
                                        "ANALOGICO": 14,
                                        "ISDBT": 24.2,
                                        "IPTV": 14
                                    }
                                }
                            ],
                            "deporte": {
                                "id": "4",
                                "nombre": "Rugby",
                                "icono": "rugby.png"
                            }
                        }
                    ],
                    "deporte": {
                        "id": "4",
                        "nombre": "Rugby",
                        "icono": "rugby.png"
                    },
                    "primerFecha": "2025-03-28 01:45:00",
                    "cantidad_eventos": 2
                },
                {
                    "id": "170",
                    "nombre": "Euroliga",
                    "eventos": [
                        {
                            "id": "76769",
                            "fecha": "2025-03-28 14:45:00",
                            "nombre": "Fenerbahce\tvs.\tBaskonia",
                            "horaDia": 2,
                            "canales": [
                                {
                                    "id": "164",
                                    "nombre": "DSPORTS / DGO"
                                }
                            ],
                            "deporte": {
                                "id": "2",
                                "nombre": "Básquet",
                                "icono": "basquet.png"
                            }
                        },
                        {
                            "id": "76770",
                            "fecha": "2025-03-28 16:15:00",
                            "nombre": "Panathinaikos\tvs.\tParis Basketball",
                            "horaDia": 2,
                            "canales": [
                                {
                                    "id": "171",
                                    "nombre": "DGO"
                                },
                                {
                                    "id": "16",
                                    "nombre": "DSPORTS 2"
                                }
                            ],
                            "deporte": {
                                "id": "2",
                                "nombre": "Básquet",
                                "icono": "basquet.png"
                            }
                        }
                    ],
                    "deporte": {
                        "id": "2",
                        "nombre": "Básquet",
                        "icono": "basquet.png"
                    },
                    "primerFecha": "2025-03-28 14:45:00",
                    "cantidad_eventos": 2
                },
                {
                    "id": "249",
                    "nombre": "Premiership Inglesa",
                    "eventos": [
                        {
                            "id": "76736",
                            "fecha": "2025-03-28 16:30:00",
                            "nombre": "Sale Sharks vs Northampton Saints",
                            "horaDia": 2,
                            "canales": [
                                {
                                    "id": "171",
                                    "nombre": "DGO"
                                },
                                {
                                    "id": "179",
                                    "nombre": "DISNEY +"
                                },
                                {
                                    "id": "161",
                                    "nombre": "ESPN 4",
                                    "plataformas": [
                                        "HD",
                                        "ANALOGICO",
                                        "ISDBT",
                                        "IPTV"
                                    ],
                                    "frecuencias": {
                                        "HD": 28,
                                        "ISDBT": 26.2,
                                        "IPTV": 22
                                    }
                                }
                            ],
                            "deporte": {
                                "id": "4",
                                "nombre": "Rugby",
                                "icono": "rugby.png"
                            }
                        }
                    ],
                    "deporte": {
                        "id": "4",
                        "nombre": "Rugby",
                        "icono": "rugby.png"
                    },
                    "primerFecha": "2025-03-28 16:30:00",
                    "cantidad_eventos": 1
                },
                {
                    "id": "536",
                    "nombre": "Boxeo",
                    "eventos": [
                        {
                            "id": "76773",
                            "fecha": "2025-03-28 21:00:00",
                            "nombre": "Título Sudamericano Supermediano: Matías Lovera\tvs. Wenceslao Mansilla",
                            "horaDia": 3,
                            "canales": [
                                {
                                    "id": "171",
                                    "nombre": "DGO"
                                },
                                {
                                    "id": "7",
                                    "nombre": "FOX SPORTS",
                                    "plataformas": [
                                        "HD",
                                        "ANALOGICO",
                                        "ISDBT",
                                        "IPTV"
                                    ],
                                    "frecuencias": {
                                        "HD": 20,
                                        "ANALOGICO": 14,
                                        "ISDBT": 24.2,
                                        "IPTV": 14
                                    }
                                }
                            ],
                            "deporte": {
                                "id": "6",
                                "nombre": "Boxeo",
                                "icono": "boxeo.png"
                            }
                        }
                    ],
                    "deporte": {
                        "id": "6",
                        "nombre": "Boxeo",
                        "icono": "boxeo.png"
                    },
                    "primerFecha": "2025-03-28 21:00:00",
                    "cantidad_eventos": 1
                }
            ],
            "eventos": [],
            "tieneEventos": true
        }
    ],
    "canales": [
        {
            "id": "171",
            "nombre": "DGO"
        },
        {
            "id": "179",
            "nombre": "DISNEY +"
        },
        {
            "id": "181",
            "nombre": "DISNEY + PREMIUM "
        },
        {
            "id": "11",
            "nombre": "DSPORTS"
        },
        {
            "id": "185",
            "nombre": "DSPORTS +",
            "plataformas": [
                "HD",
                "ANALOGICO",
                "ISDBT",
                "IPTV"
            ]
        },
        {
            "id": "164",
            "nombre": "DSPORTS / DGO"
        },
        {
            "id": "16",
            "nombre": "DSPORTS 2"
        },
        {
            "id": "39",
            "nombre": "ESPN 2",
            "plataformas": [
                "HD",
                "ANALOGICO",
                "ISDBT",
                "IPTV"
            ],
            "frecuencias": {
                "HD": 26,
                "ANALOGICO": 20,
                "ISDBT": 25.5,
                "IPTV": 20
            }
        },
        {
            "id": "25",
            "nombre": "ESPN 3",
            "plataformas": [
                "HD",
                "ANALOGICO",
                "ISDBT",
                "IPTV"
            ],
            "frecuencias": {
                "HD": 27,
                "ANALOGICO": 21,
                "ISDBT": 25.6,
                "IPTV": 21
            }
        },
        {
            "id": "161",
            "nombre": "ESPN 4",
            "plataformas": [
                "HD",
                "ANALOGICO",
                "ISDBT",
                "IPTV"
            ],
            "frecuencias": {
                "HD": 28,
                "ISDBT": 26.2,
                "IPTV": 22
            }
        },
        {
            "id": "7",
            "nombre": "FOX SPORTS",
            "plataformas": [
                "HD",
                "ANALOGICO",
                "ISDBT",
                "IPTV"
            ],
            "frecuencias": {
                "HD": 20,
                "ANALOGICO": 14,
                "ISDBT": 24.2,
                "IPTV": 14
            }
        },
        {
            "id": "15",
            "nombre": "FOX SPORTS 2",
            "plataformas": [
                "HD",
                "ANALOGICO",
                "ISDBT",
                "IPTV"
            ],
            "frecuencias": {
                "HD": 21,
                "ANALOGICO": 15,
                "ISDBT": 24.3,
                "IPTV": 15
            }
        },
        {
            "id": "20",
            "nombre": "TYC SPORTS",
            "plataformas": [
                "HD",
                "ANALOGICO",
                "ISDBT",
                "IPTV"
            ],
            "frecuencias": {
                "HD": 23,
                "ANALOGICO": 17,
                "ISDBT": 24.5,
                "IPTV": 17
            }
        },
        {
            "id": "50",
            "nombre": "TYC SPORTS PLAY"
        }
    ],
    "hoy": "2025-03-26",
    "firma": {
        "mail": "leandromanna@gmail.com // https://mannaleandro.netlify.app/",
        "nombre": "Leandro A. Manna"
    }
}